[
  {
    "createSurface": {
      "surfaceId": "widget_weather",
      "catalogId": "standard_catalog_v0.9",
      "sendDataModel": true,
      "designTokens": {
        "Colors.Blue": {
          "value": "#007aff",
          "collection": "System Colors"
        },
        "Main.beerus": {
          "value": "#e2e2e2",
          "collection": "Colors"
        }
      }
    }
  },
  {
    "updateComponents": {
      "surfaceId": "widget_weather",
      "components": [
        {
          "id": "sun",
          "component": "Icon",
          "iconName": "sun",
          "svgData": "<svg width=\"32\" height=\"32\" viewBox=\"0 0 32 32\" fill=\"none\" xmlns=\"http://www.w3.org/2000/svg\">\n<g clip-path=\"url(#clip0_32632_1213)\">\n<path d=\"M16 1.33333V4M16 28V30.6667M5.62666 5.62667L7.51999 7.52M24.48 24.48L26.3733 26.3733M1.33333 16H3.99999M28 16H30.6667M5.62666 26.3733L7.51999 24.48M24.48 7.52L26.3733 5.62667M22.6667 16C22.6667 19.6819 19.6819 22.6667 16 22.6667C12.3181 22.6667 9.33333 19.6819 9.33333 16C9.33333 12.3181 12.3181 9.33333 16 9.33333C19.6819 9.33333 22.6667 12.3181 22.6667 16Z\" stroke=\"#FFD600\" stroke-width=\"3\" stroke-linecap=\"round\" stroke-linejoin=\"round\"/>\n</g>\n<defs>\n<clipPath id=\"clip0_32632_1213\">\n<rect width=\"32\" height=\"32\" fill=\"white\"/>\n</clipPath>\n</defs>\n</svg>\n",
          "style": {
            "width": 32,
            "height": 32,
            "backgroundColor": "#ffffff",
            "paddingTop": 0,
            "paddingRight": 0,
            "paddingBottom": 0,
            "paddingLeft": 0,
            "mainAxisAlignment": "min",
            "crossAxisAlignment": "min"
          }
        },
        {
          "id": "aubrey_tx",
          "component": "Text",
          "text": "${/aubrey_tx/text}",
          "style": {
            "width": 64,
            "height": 16,
            "color": "{Main.beerus}",
            "fontSize": 12,
            "fontFamily": "DM Sans",
            "fontWeight": "Bold",
            "lineHeight": 16,
            "textAlign": "center",
            "layoutSizingHorizontal": "hug",
            "layoutSizingVertical": "hug"
          }
        },
        {
          "id": "75_f_clear_sky",
          "component": "Text",
          "text": "${/75_f_clear_sky/text}",
          "style": {
            "width": 124,
            "height": 28,
            "color": "{Main.beerus}",
            "fontSize": 18,
            "fontFamily": "DM Sans",
            "fontWeight": "Medium",
            "lineHeight": 28,
            "textAlign": "center",
            "layoutSizingHorizontal": "hug",
            "layoutSizingVertical": "hug"
          }
        },
        {
          "id": "root",
          "component": "Card",
          "children": {
            "explicitList": [
              "sun",
              "aubrey_tx",
              "75_f_clear_sky"
            ]
          },
          "style": {
            "width": 156,
            "height": 128,
            "backgroundColor": "{Colors.Blue}",
            "cornerRadius": 16,
            "borderColor": "{Colors.Blue}",
            "borderWidth": 1,
            "paddingTop": 16,
            "paddingRight": 16,
            "paddingBottom": 16,
            "paddingLeft": 16,
            "gap": 10,
            "mainAxisAlignment": "min",
            "crossAxisAlignment": "min",
            "layoutSizingHorizontal": "hug",
            "layoutSizingVertical": "hug",
            "shadows": [
              {
                "x": 0,
                "y": 4,
                "blur": 4,
                "color": "#00000040"
              }
            ]
          }
        }
      ]
    }
  },
  {
    "updateDataModel": {
      "surfaceId": "widget_weather",
      "path": "/",
      "value": {
        "aubrey_tx": {
          "text": "Aubrey, TX"
        },
        "75_f_clear_sky": {
          "text": "75° F, clear sky"
        }
      }
    }
  }
]